MANIFEST.in
README.rst
setup.py
dashboard/__init__.py
dashboard/admin.py
dashboard/enumerations.py
dashboard/models.py
dashboard/tests.py
dashboard/urls.py
dashboard/views.py
dashboard/locale/prs/LC_MESSAGES/django.mo
dashboard/locale/prs/LC_MESSAGES/django.po
dashboard/locale/ps/LC_MESSAGES/django.mo
dashboard/locale/ps/LC_MESSAGES/django.po
dashboard/templates/custombase.html
dashboard/templates/custombase_asli.html
dashboard/templates/dash_baseline.html
dashboard/templates/dash_main.html
dashboard/templates/dashboard_base.html
dashboard/templates/links_title.html
dashboard/templates/qlink_list.html
dashboard/templates/qlink_span.html
dashboard/templates/pages/accessibility.html
dashboard/templates/pages/avalancherisk.html
dashboard/templates/pages/avalcheforecast.html
dashboard/templates/pages/baseline.html
dashboard/templates/pages/earthquake.html
dashboard/templates/pages/floodforecast.html
dashboard/templates/pages/floodrisk.html
dashboard/templates/pages/landsliderisk.html
dashboard/templates/pages/links.html
dashboard/templates/pages/naturaldisaster.html
dashboard/templates/pages/security.html
dashboard/templates/pages/weather.html
dashboard/templatetags/__init__.py
dashboard/templatetags/__init__.pyc
dashboard/templatetags/app_filters.py
dashboard/templatetags/app_filters.pyc
isdc_dashboard.egg-info/PKG-INFO
isdc_dashboard.egg-info/SOURCES.txt
isdc_dashboard.egg-info/dependency_links.txt
isdc_dashboard.egg-info/top_level.txt